setup.py
pydeployer/__init__.py
pydeployer/__main__.py
pydeployer/client.py
pydeployer/deploy.py
pydeployer/security.py
pydeployer/user.py
pydeployer.egg-info/PKG-INFO
pydeployer.egg-info/SOURCES.txt
pydeployer.egg-info/dependency_links.txt
pydeployer.egg-info/entry_points.txt
pydeployer.egg-info/requires.txt
pydeployer.egg-info/top_level.txt
pydeployer.egg-info/zip-safe