Metadata-Version: 1.1
Name: pydeployer
Version: 0.1.1
Summary: Python toolkit for deploying local project to a remote server.
Home-page: https://github.com/jkuijt/pydeployer
Author: Jasper Kuijt
Author-email: jasperkuijt@live.nl
License: MIT
Platform: UNKNOWN
Classifier: Programming Language :: Python
